<?xml version='1.0' encoding='UTF-8'?>
<definitions xmlns="http://www.omg.org/spec/BPMN/20100524/MODEL" xmlns:xsi="http://www.w3.org/2001/XMLSchema-instance" xmlns:xsd="http://www.w3.org/2001/XMLSchema" xmlns:activiti="http://activiti.org/bpmn" xmlns:bpmndi="http://www.omg.org/spec/BPMN/20100524/DI" xmlns:omgdc="http://www.omg.org/spec/DD/20100524/DC" xmlns:omgdi="http://www.omg.org/spec/DD/20100524/DI" typeLanguage="http://www.w3.org/2001/XMLSchema" expressionLanguage="http://www.w3.org/1999/XPath" targetNamespace="http://www.activiti.org/processdef" xmlns:modeler="http://activiti.com/modeler" modeler:version="1.0en" modeler:exportDateTime="20160801201250908" modeler:modelId="1" modeler:modelVersion="9" modeler:modelLastUpdated="1470073741442">
  <process id="Create_Edit_Users" name="Create_Edit_Users" isExecutable="true">
    <startEvent id="startEvent1"/>
    <userTask id="sid-C8247EB6-9B6C-454E-8604-4A70E95E3D47" name="Edit_User_Task" activiti:assignee="$INITIATOR" activiti:formKey="2">
      <extensionElements>
        <modeler:allow-send-email><![CDATA[true]]></modeler:allow-send-email>
        <modeler:form-reference-id><![CDATA[2]]></modeler:form-reference-id>
        <modeler:form-reference-name><![CDATA[Health_User_Form]]></modeler:form-reference-name>
        <modeler:activiti-idm-initiator><![CDATA[true]]></modeler:activiti-idm-initiator>
      </extensionElements>
    </userTask>
    <endEvent id="sid-B885AE38-61C1-4B0B-9DB1-90E5A2CAA6D8"/>
    <sequenceFlow id="sid-A486EF29-6F2B-4841-9157-2152B6994BF5" sourceRef="sid-C8247EB6-9B6C-454E-8604-4A70E95E3D47" targetRef="sid-B885AE38-61C1-4B0B-9DB1-90E5A2CAA6D8"/>
    <sequenceFlow id="sid-CA020003-F357-4A20-90A4-6A6693EB3691" sourceRef="startEvent1" targetRef="sid-C8247EB6-9B6C-454E-8604-4A70E95E3D47"/>
  </process>
  <bpmndi:BPMNDiagram id="BPMNDiagram_Create_Edit_Users">
    <bpmndi:BPMNPlane bpmnElement="Create_Edit_Users" id="BPMNPlane_Create_Edit_Users">
      <bpmndi:BPMNShape bpmnElement="startEvent1" id="BPMNShape_startEvent1">
        <omgdc:Bounds height="30.0" width="30.0" x="195.0" y="167.0"/>
      </bpmndi:BPMNShape>
      <bpmndi:BPMNShape bpmnElement="sid-C8247EB6-9B6C-454E-8604-4A70E95E3D47" id="BPMNShape_sid-C8247EB6-9B6C-454E-8604-4A70E95E3D47">
        <omgdc:Bounds height="80.0" width="130.0" x="315.0" y="142.0"/>
      </bpmndi:BPMNShape>
      <bpmndi:BPMNShape bpmnElement="sid-B885AE38-61C1-4B0B-9DB1-90E5A2CAA6D8" id="BPMNShape_sid-B885AE38-61C1-4B0B-9DB1-90E5A2CAA6D8">
        <omgdc:Bounds height="28.0" width="28.0" x="540.0" y="168.0"/>
      </bpmndi:BPMNShape>
      <bpmndi:BPMNEdge bpmnElement="sid-CA020003-F357-4A20-90A4-6A6693EB3691" id="BPMNEdge_sid-CA020003-F357-4A20-90A4-6A6693EB3691">
        <omgdi:waypoint x="225.0" y="182.0"/>
        <omgdi:waypoint x="315.0" y="182.0"/>
      </bpmndi:BPMNEdge>
      <bpmndi:BPMNEdge bpmnElement="sid-A486EF29-6F2B-4841-9157-2152B6994BF5" id="BPMNEdge_sid-A486EF29-6F2B-4841-9157-2152B6994BF5">
        <omgdi:waypoint x="445.0" y="182.0"/>
        <omgdi:waypoint x="540.0" y="182.0"/>
      </bpmndi:BPMNEdge>
    </bpmndi:BPMNPlane>
  </bpmndi:BPMNDiagram>
</definitions>